watr/__init__.py
watr/entity.py
watr/util.py
watr/watrapi.py
watr/watrentity.py
watr/watrexceptions.py
watr/watrsprinklersystem.py
watr/watrsystem.py
watr/watrzone.py
watr-0.0.6.dist-info/METADATA
watr-0.0.6.dist-info/WHEEL
watr-0.0.6.dist-info/top_level.txt
watr-0.0.6.dist-info/RECORD
