Metadata-Version: 2.1
Name: watr
Version: 0.0.6
Summary: A python library to control a Watr system
Home-page: https://capstone-cs.eng.utah.edu/Watr
Author: Watr
Author-email: watr@peasenet.com.com
Project-URL: Bug Tracker, https://capstone-cs.eng.utah.edu/Watr/Watr/issues
Classifier: Programming Language :: Python :: 3
Classifier: License :: OSI Approved :: MIT License
Requires-Python: >=3.8
